qaeval/__init__.py
qaeval/answer_selection.py
qaeval/metric.py
qaeval/version.py
qaeval/answering/__init__.py
qaeval/answering/model.py
qaeval/answering/utils.py
qaeval/generation/__init__.py
qaeval/generation/dataset_reader.py
qaeval/generation/model.py
qaeval/generation/predictor.py
qaeval/generation/util.py
qaeval/scoring/__init__.py
qaeval/scoring/lerc/__init__.py
qaeval/scoring/lerc/lerc_dataset_reader.py
qaeval/scoring/lerc/lerc_model.py
qaeval/scoring/lerc/lerc_predictor.py
qaeval/scoring/lerc/pretrain_model.py
qaeval/scoring/scorers/__init__.py
qaeval/scoring/scorers/em.py
qaeval/scoring/scorers/f1.py
qaeval/scoring/scorers/is_answered.py
qaeval/scoring/scorers/lerc.py
qaeval/scoring/scorers/meta.py
qaeval/scoring/scorers/scorer.py
qaeval/tests/__init__.py
qaeval/tests/answer_selection_test.py
qaeval/tests/metric_test.py
qaeval/tests/answering/__init__.py
qaeval/tests/answering/model_test.py
qaeval/tests/answering/utils_test.py
qaeval/tests/generation/__init__.py
qaeval/tests/generation/model_test.py
qaeval/tests/scoring/__init__.py
qaeval/tests/scoring/scorers/__init__.py
qaeval/tests/scoring/scorers/em_test.py
qaeval/tests/scoring/scorers/f1_test.py
qaeval/tests/scoring/scorers/is_answered_test.py
qaeval/tests/scoring/scorers/lerc_test.py
qaeval/tests/scoring/scorers/meta_test.py
qaeval/tests/scoring/scorers/scorer_test.py
qaeval-0.1.0.dist-info/LICENSE
qaeval-0.1.0.dist-info/METADATA
qaeval-0.1.0.dist-info/WHEEL
qaeval-0.1.0.dist-info/top_level.txt
qaeval-0.1.0.dist-info/RECORD
