Metadata-Version: 2.1
Name: qaeval
Version: 0.1.0
Summary: A package for evaluating the content of summaries through question-answering
Home-page: https://github.com/danieldeutsch/qaeval
Author: Daniel Deutsch
License: UNKNOWN
Platform: UNKNOWN
Requires-Python: >=3.6
Requires-Dist: allennlp (==1.1.0)
Requires-Dist: click (==7.1.2)
Requires-Dist: edlib
Requires-Dist: spacy (==2.2.4)
Requires-Dist: torch (==1.6.0)
Requires-Dist: transformers (==3.0.2)
Requires-Dist: urllib3 (>=1.25.10)
